setup.py
PytonPyt/__init__.py
PytonPyt/m_one.py
PytonPyt/m_two.py
PytonPyt.egg-info/PKG-INFO
PytonPyt.egg-info/SOURCES.txt
PytonPyt.egg-info/dependency_links.txt
PytonPyt.egg-info/top_level.txt