Metadata-Version: 2.1
Name: PytonPyt
Version: 0.0.1
Summary: My Package
Home-page: UNKNOWN
Author: Your Name
Author-email: olgahaipriv7177@gmail.com
License: UNKNOWN
Platform: UNKNOWN
